jalalidate/__init__.py
jalalidate/jalali.py
jalalidate-0.1.2.dist-info/LICENSE.txt
jalalidate-0.1.2.dist-info/METADATA
jalalidate-0.1.2.dist-info/WHEEL
jalalidate-0.1.2.dist-info/top_level.txt
jalalidate-0.1.2.dist-info/RECORD
