Metadata-Version: 2.1
Name: jalalidate
Version: 0.1.2
Summary: change date between gregorian and jalali date
Home-page: https://github.com/j-jahedi/jalali-date
Download-URL: https://github.com/j-jahedi/jalali-date/archive/refs/heads/master.zip
Author: Javad Jahedi
Author-email: javad.jahedi@gmail.com
License: MIT
Keywords: Jalali,Jalali-date
Platform: UNKNOWN
Classifier: Programming Language :: Python :: 3.8
License-File: LICENSE.txt
